MCD12C1_2019_v006/MCD12C1.A2019001.006.2020220162300.jpeg
MCD12C1_2019_v006/MCD12C1.A2019001.006.2020220162300.jpeg.aux.xml
MCD12C1_2019_v006/MCD12C1.A2019001.006.2020220162300.tif
MCD12C1_2019_v006/MCD12C1_2019_v006.py
MCD12C1_2019_v006/__init__.py
MCD12C1_2019_v006/version.txt
MCD12C1_2019_v006-1.0.1.dist-info/LICENSE
MCD12C1_2019_v006-1.0.1.dist-info/METADATA
MCD12C1_2019_v006-1.0.1.dist-info/WHEEL
MCD12C1_2019_v006-1.0.1.dist-info/top_level.txt
MCD12C1_2019_v006-1.0.1.dist-info/RECORD
