Metadata-Version: 2.1
Name: MCD12C1_2019_v006
Version: 1.0.1
Summary: MODIS/Terra+Aqua Land Cover Type CMG Yearly L3 Global 0.05 Deg 2019 Collection 6 Dataset Python Tool
Author-email: "Gregory H. Halverson" <gregory.h.halverson@jpl.nasa.gov>
Project-URL: Homepage, https://github.com/JPL-Evapotranspiration-Algorithms/MCD12C1_2019_v006
Classifier: Programming Language :: Python :: 3
Classifier: Operating System :: OS Independent
Requires-Python: >=3.10
License-File: LICENSE
Requires-Dist: numpy
Requires-Dist: rasters
